README.rst
setup.cfg
setup.py
ar_too/__init__.py
ar_too/api.py
ar_too/cli.py
ar_too/exceptions.py
ar_too/utils.py
ar_too.egg-info/PKG-INFO
ar_too.egg-info/SOURCES.txt
ar_too.egg-info/dependency_links.txt
ar_too.egg-info/entry_points.txt
ar_too.egg-info/not-zip-safe
ar_too.egg-info/requires.txt
ar_too.egg-info/top_level.txt