Metadata-Version: 1.1
Name: ar-too
Version: 0.4
Summary: Artifactory configuration tool
Home-page: https://github.com/brain461/ar_too.git
Author: MCP CI
Author-email: mcp-ci@mirantis.com
License: Apache
Download-URL: https://github.com/brain461/ar_too/tarball/0.4
Keywords: ar_too
Platform: UNKNOWN
Classifier: Development Status :: 2 - Pre-Alpha
Classifier: Intended Audience :: Developers
Classifier: Intended Audience :: Information Technology
Classifier: License :: OSI Approved :: Apache Software License
Classifier: Natural Language :: English
Classifier: Programming Language :: Python :: 2
Classifier: Programming Language :: Python :: 2.6
Classifier: Programming Language :: Python :: 2.7
